aiochlite/__init__.py
aiochlite/client.py
aiochlite/exceptions.py
aiochlite/http_client.py
aiochlite/converters/__init__.py
aiochlite/converters/_type_parsing.py
aiochlite/converters/rowbinary.py
aiochlite/converters/to_clickhouse.py
aiochlite/converters/to_json.py
aiochlite/core/__init__.py
aiochlite/core/client.py
aiochlite/core/external_data.py
aiochlite/core/models.py
aiochlite-1.0.0.dist-info/licenses/LICENSE
aiochlite-1.0.0.dist-info/METADATA
aiochlite-1.0.0.dist-info/WHEEL
aiochlite-1.0.0.dist-info/top_level.txt
aiochlite-1.0.0.dist-info/RECORD
