Metadata-Version: 2.4
Name: aiochlite
Version: 1.0.0
Summary: Lightweight asynchronous ClickHouse client for Python built on asyncio.
Author: darkstussy
License: MIT License
Project-URL: Homepage, https://github.com/darkstussy/aiochlite
Project-URL: Issues, https://github.com/darkstussy/aiochlite/issues
Classifier: Programming Language :: Python :: 3
Classifier: Programming Language :: Python :: 3.12
Classifier: Programming Language :: Python :: 3.13
Classifier: Programming Language :: Python :: 3.14
Classifier: Framework :: AsyncIO
Classifier: Intended Audience :: Developers
Classifier: Operating System :: OS Independent
Classifier: Topic :: Internet :: WWW/HTTP :: Indexing/Search
Classifier: Topic :: Software Development :: Libraries :: Application Frameworks
Requires-Python: >=3.12
License-File: LICENSE
Requires-Dist: aiohttp~=3.13.2
Dynamic: license-file
